SSVDpkg_663proj2021S/SSVDversion1.py
SSVDpkg_663proj2021S/SSVDversion2.py
SSVDpkg_663proj2021S/SSVDversion3.py
SSVDpkg_663proj2021S/SSVDversion4.py
SSVDpkg_663proj2021S/SSVDversion5.py
SSVDpkg_663proj2021S/__init__.py
SSVDpkg_663proj2021S/functions.py
SSVDpkg_663proj2021S-0.1.dist-info/LICENSE
SSVDpkg_663proj2021S-0.1.dist-info/METADATA
SSVDpkg_663proj2021S-0.1.dist-info/WHEEL
SSVDpkg_663proj2021S-0.1.dist-info/top_level.txt
SSVDpkg_663proj2021S-0.1.dist-info/RECORD
